lfsdata-0.0.2-py3.10-nspkg.pth
lfsdata/git_data_loader.py
tests/__init__.py
tests/test_download.py
lfsdata-0.0.2.dist-info/LICENSE
lfsdata-0.0.2.dist-info/METADATA
lfsdata-0.0.2.dist-info/WHEEL
lfsdata-0.0.2.dist-info/namespace_packages.txt
lfsdata-0.0.2.dist-info/top_level.txt
lfsdata-0.0.2.dist-info/RECORD
