Metadata-Version: 2.1
Name: lfsdata
Version: 0.0.2
Home-page: https://github.com/arushadev/lfsdata
Author: Arusha Developers
Author-email: info@arusha.dev
Maintainer: Hamed Khademi Khaledi
Maintainer-email: khaledihkh@gmail.com
Classifier: Development Status :: 1 - Planning
Classifier: Programming Language :: Python :: 3.0
Classifier: Topic :: Utilities
Classifier: License :: OSI Approved :: GNU Lesser General Public License v2 (LGPLv2)
Requires-Python: >=3.11
License-File: LICENSE
Requires-Dist: setuptools >=45.0
Requires-Dist: coloredlogs
Requires-Dist: python-gitlab
